[
  {
    "id": "q_1775171729907_lqzkay",
    "text": "メタプラネット($3350)の株価、ビットコイン連動から脱却中？\n\n1月：BTC+8%、メタプラ-12%\n昨年12月：BTC+14%、メタプラ+22%\n\n相関係数0.85→0.42に低下。\n\nAIデータセンター電力需要でエネルギー株注目の中、BTC採掘の電力コストも論点に。核融合・SMR実用化までは従来電源に依存だが、メタプラの投資判断に影響する？\n\nBTC保有企業として見るか、日本株として見るか。",
    "score": {
      "scores": {
        "buzz": 8,
        "hook": 9,
        "value": 8,
        "data": 9,
        "unique": 7,
        "discussion": 9,
        "bookmark": 7,
        "tempo": 8,
        "persona": 8,
        "ng_check": 10
      },
      "average": 8.3
    },
    "pattern_id": "P08",
    "hook_id": "H30",
    "theme": "メタプラネット・ビットコイン関連（賛否両論あるネタとして積極的に取り上げる）",
    "tweet_type": "standard",
    "research_id": "r_1774389937674_gifc",
    "created_at": "2026-04-02T23:15:29.908Z"
  },
  {
    "id": "q_1775171729908_3ep1z4",
    "text": "$NIKKEI、午前で394円高の5万1961円。\n\n注目すべきは出来高。前日比+15%増の12.8億株で、明らかに「待ってました」の買いが入ってる。中東リスクが一服したタイミングで、溜まってた買い圧力が一気に放出。\n\n期末配当取りの思惑もあるが、それより大きいのは5万2000円の心理的節目を意識した仕込み。ここ抜けたら次は5万3000円だし。\n\nただし午前高値から縮小してるのが気になる。本当の勝負は後場。",
    "score": {
      "scores": {
        "buzz": 8,
        "hook": 9,
        "value": 8,
        "data": 9,
        "unique": 7,
        "discussion": 8,
        "bookmark": 7,
        "tempo": 8,
        "persona": 9,
        "ng_check": 10
      },
      "average": 8.3
    },
    "pattern_id": "P02",
    "hook_id": "H12",
    "theme": "日本株個別銘柄分析",
    "tweet_type": "standard",
    "research_id": "r_1774394913256_dtmg",
    "created_at": "2026-04-02T23:15:29.908Z"
  },
  {
    "id": "q_1775171729908_zssiyl",
    "text": "日銀、政策金利0.75%据え置き。\n\nでも次回利上げ予想は2026年後半にズレ込み。これ、円安トレンド継続ってことだよな？\n\n・輸出企業の業績押し上げ継続\n・金融株への圧迫は一旦回避\n・インバウンド需要も底堅く推移\n\nイラン情勢で原油価格見極めるって言ってるけど、実際は米国利下げ待ちでしょ。円安メリット銘柄、まだ買えるタイミングかも。",
    "score": {
      "scores": {
        "buzz": 8,
        "hook": 8,
        "value": 8,
        "data": 7,
        "unique": 8,
        "discussion": 8,
        "bookmark": 7,
        "tempo": 8,
        "persona": 8,
        "ng_check": 9
      },
      "average": 7.9
    },
    "pattern_id": "P12",
    "hook_id": "H06",
    "theme": "今日のバズニュース（海外）",
    "tweet_type": "standard",
    "research_id": "r_1774394913256_3ref",
    "created_at": "2026-04-02T23:15:29.908Z"
  },
  {
    "id": "q_1775171729908_j5mfxf",
    "text": "$NVDA の12ヶ月PER、現在33倍。\n\nこれをどう見るかで投資家のレベルがわかる。\n\n高いと思った人→成長株投資に向いてない\n安いと思った人→データ中毒\n\n重要なのはPEGレシオ。予想成長率40%で計算すると0.8倍。実はバリュー株なんだよね。\n\n機械受注の一時減も、AI投資シフトの表れ。従来設備<生成AI投資の構図が鮮明になってきた。",
    "score": {
      "scores": {
        "buzz": 8,
        "hook": 9,
        "value": 9,
        "data": 9,
        "unique": 8,
        "discussion": 9,
        "bookmark": 7,
        "tempo": 8,
        "persona": 9,
        "ng_check": 10
      },
      "average": 8.6
    },
    "pattern_id": "P06",
    "hook_id": "H05",
    "theme": "米国株個別銘柄分析",
    "tweet_type": "standard",
    "research_id": "r_1774394913256_85gg",
    "created_at": "2026-04-02T23:15:29.908Z"
  },
  {
    "id": "q_1775171729908_xcrtiw",
    "text": "防衛費GDP2%達成なら、年間予算は11兆円規模に。現在の5.4兆円から倍増だ。\n\n三菱重工業（$7011）：F-35戦闘機の最終組立\nIHI（$7013）：ジェットエンジン技術\n川崎重工（$7012）：輸送機・ヘリ開発\n\nこの3社だけで防衛売上高は計1.2兆円。市場拡大で取り合いじゃなく、パイ自体が大きくなる。\n\n宇宙分野も2030年までに8兆円市場目標。国策銘柄、まだ織り込み不十分じゃない？",
    "score": {
      "scores": {
        "buzz": 8,
        "hook": 9,
        "value": 9,
        "data": 9,
        "unique": 7,
        "discussion": 8,
        "bookmark": 9,
        "tempo": 8,
        "persona": 8,
        "ng_check": 10
      },
      "average": 8.5
    },
    "pattern_id": "P15",
    "hook_id": "H25",
    "theme": "テーマ投資（半導体・AI・防衛・原子力・宇宙・Physical AI）",
    "tweet_type": "standard",
    "research_id": "r_1774394913256_x8er",
    "created_at": "2026-04-02T23:15:29.908Z"
  },
  {
    "id": "q_1775171729908_5mhbfa",
    "text": "2026年IPO市場、60-70社上場予想だが過去データ見ると面白い。\n\n📊 IPO市場推移\n2021年：125社（バブル期）\n2022年：91社\n2023年：76社\n2024年：80社\n2025年：約70社（予想）\n2026年：60-70社（予想）\n\nUSJ、スマートニュースの大型案件控えてるけど、これ実質的に「量から質」への転換期だよね。\n\n市場規模縮小してるのに大型案件期待って、結局小型IPOが淘汰されてるだけじゃん。投資家にとってはむしろプラスかも。",
    "score": {
      "scores": {
        "buzz": 7,
        "hook": 8,
        "value": 8,
        "data": 9,
        "unique": 7,
        "discussion": 8,
        "bookmark": 8,
        "tempo": 7,
        "persona": 8,
        "ng_check": 10
      },
      "average": 8
    },
    "pattern_id": "P01",
    "hook_id": "H10",
    "theme": "今日のバズニュース（海外）",
    "tweet_type": "standard",
    "research_id": "r_1774394913256_s5ta",
    "created_at": "2026-04-02T23:15:29.908Z"
  },
  {
    "text": "今週の日本株、外国人4906億円売り越し。6カ月ぶりの大きさ。\n\n中東情勢＋日銀利上げ観測＋米金融政策の変化。三重苦で需給が一気に悪化した。\n\n日経平均1866円安も、これ調整の入り口だろ。地政学リスクが長期化すれば、まだ下がる。\n\n逆に言えば、ここが買い場になる可能性も高い。強い銘柄を見極める時期だな。",
    "tweet_type": "standard",
    "score": 8.2,
    "theme": "外国人投資家売り越し",
    "cashtags": [],
    "generated_at": "2026-04-03T14:32:44.591Z",
    "source": "content-poster"
  },
  {
    "text": "外国人、4906億円の売り越し。6カ月ぶりの大きさ。\n\n中東情勢の長期化で完全にリスクオフモード。日経も1866円安で5万3372円。これ、まだ底じゃないだろ。\n\n日銀は据え置きだが、4月利上げ観測で市場はびびってる。原油高でインフレ懸念も浮上。\n\n正直、こういう時こそチャンス。海外勢が投げ売りした優良株を拾うタイミングなんだよな。",
    "tweet_type": "standard",
    "score": 8.2,
    "theme": "週間マーケット振り返り",
    "cashtags": [],
    "generated_at": "2026-04-03T14:32:54.987Z",
    "source": "content-poster"
  },
  {
    "text": "海外勢、4906億円の日本株売り越し。6カ月ぶりの大きさなんだよな。\n\n中東情勢の長期化で完全にリスクオフモード。日経平均1866円安の衝撃もあって、外国人がガンガン売ってきてる。\n\nただ、これだけ売られたら逆に買い場近いんじゃないか？需給最悪の時こそチャンス。",
    "tweet_type": "standard",
    "score": 8.2,
    "theme": "外国人投資家売り越し分析",
    "cashtags": [],
    "generated_at": "2026-04-03T14:33:04.565Z",
    "source": "content-poster"
  }
]